cls_luigi/__init__.py
cls_luigi/cls_tasks.py
cls_luigi/inhabitation_task.py
cls_luigi/unique_task_pipeline_validator.py
cls_luigi/repo_visualizer/__init__.py
cls_luigi/repo_visualizer/app.js
cls_luigi/repo_visualizer/config.json
cls_luigi/repo_visualizer/dynamic_json_repo.py
cls_luigi/repo_visualizer/index.html
cls_luigi/repo_visualizer/json_io.py
cls_luigi/repo_visualizer/static_json_repo.py
cls_luigi/repo_visualizer/style.css
cls_luigi/repo_visualizer/visualizer.py
cls_luigi/repo_visualizer/js_lib/d3.js
cls_luigi/repo_visualizer/js_lib/dagre-d3.js
cls_luigi/tests/__init__.py
cls_luigi/tests/test_inhabitation_task_repometa.py
cls_luigi-0.1.1.dist-info/AUTHORS.rst
cls_luigi-0.1.1.dist-info/LICENSE
cls_luigi-0.1.1.dist-info/METADATA
cls_luigi-0.1.1.dist-info/WHEEL
cls_luigi-0.1.1.dist-info/top_level.txt
cls_luigi-0.1.1.dist-info/RECORD
