Metadata-Version: 2.1
Name: cls-luigi
Version: 0.1.1
Summary: CLS-Luigi is an innovative pipeline tool designed to streamline the creation and execution of algorithmic pipelines by harnessing the power of combinatory logic.
Home-page: https://github.com/cls-python/cls-luigi
Author: Jan Bessai
Author-email: jan.bessai@tu-dortmund.de
Maintainer: Daniel Scholtyssek
Maintainer-email: daniel.scholtyssek@tu-dortmund.de
License: Apache License (2.0)
Project-URL: Bug Tracker, https://github.com/cls-python/cls-luigi/issues
Project-URL: Documentation, https://cls-python.github.io/cls-luigi
Project-URL: Source Code, https://github.com/cls-python/cls-luigi
Keywords: cls-luigi
Classifier: Development Status :: 3 - Alpha
Classifier: Intended Audience :: Science/Research
Classifier: Intended Audience :: Developers
Classifier: License :: OSI Approved :: Apache Software License
Classifier: Natural Language :: English
Classifier: Programming Language :: Python :: 3.10
Classifier: Programming Language :: Python :: 3.11
Classifier: Operating System :: Microsoft :: Windows
Classifier: Operating System :: Unix
Classifier: Operating System :: MacOS
Requires-Python: >=3.10
License-File: LICENSE
License-File: AUTHORS.rst
Requires-Dist: cls-python
Requires-Dist: luigi
Requires-Dist: requests
